diffusionq/__init__.py
diffusionq-0.1.0.dist-info/METADATA
diffusionq-0.1.0.dist-info/WHEEL
diffusionq-0.1.0.dist-info/top_level.txt
diffusionq-0.1.0.dist-info/RECORD
