Metadata-Version: 2.1
Name: diffusionq
Version: 0.1.0
Summary: quantizing your diffusion models efficiently and accurately
Author: Yefei
Author-email: billhe786@gmail.com
Classifier: Programming Language :: Python :: 3
Classifier: License :: OSI Approved :: MIT License
Classifier: Operating System :: OS Independent
Requires-Python: >=3.6
Requires-Dist: numpy
Requires-Dist: torch
